cfn_kafka_admin/__init__.py
cfn_kafka_admin/cfn_kafka_admin.py
cfn_kafka_admin/cfn_resources_definitions/__init__.py
cfn_kafka_admin/cfn_resources_definitions/custom.py
cfn_kafka_admin/cfn_resources_definitions/resource.py
cfn_kafka_admin/cli.py
cfn_kafka_admin/common.py
cfn_kafka_admin/kafka_resources/__init__.py
cfn_kafka_admin/kafka_resources/acls.py
cfn_kafka_admin/kafka_resources/topics/__init__.py
cfn_kafka_admin/kafka_resources/topics/create.py
cfn_kafka_admin/kafka_resources/topics/delete.py
cfn_kafka_admin/kafka_resources/topics/update.py
cfn_kafka_admin/lambda_functions/__init__.py
cfn_kafka_admin/lambda_functions/acls.py
cfn_kafka_admin/lambda_functions/schemas.py
cfn_kafka_admin/lambda_functions/topics.py
cfn_kafka_admin/lambda_functions/utils.py
cfn_kafka_admin/models/__init__.py
cfn_kafka_admin/models/admin.py
cfn_kafka_admin/specs/__init__.py
cfn_kafka_admin/specs/aws-cfn-kafka-admin-provider-schema.json
cfn_kafka_admin/specs/ews-kafka-acl.json
cfn_kafka_admin/specs/ews-kafka-parameters.json
cfn_kafka_admin/specs/ews-kafka-schema.json
cfn_kafka_admin/specs/ews-kafka-topic.json
cfn_kafka_admin-0.7.0.dist-info/AUTHORS.rst
cfn_kafka_admin-0.7.0.dist-info/LICENSE
cfn_kafka_admin-0.7.0.dist-info/METADATA
cfn_kafka_admin-0.7.0.dist-info/WHEEL
cfn_kafka_admin-0.7.0.dist-info/entry_points.txt
cfn_kafka_admin-0.7.0.dist-info/RECORD
