Metadata-Version: 2.1
Name: cfn_kafka_admin
Version: 0.7.0
Summary: AWS CloudFormation Resources to manage Kafka
License: MPL-2.0
Author: John Mille
Author-email: john@compose-x.io
Requires-Python: >=3.9,<4.0
Classifier: License :: OSI Approved
Classifier: License :: OSI Approved :: Mozilla Public License 2.0 (MPL 2.0)
Classifier: Natural Language :: English
Classifier: Programming Language :: Python :: 3
Classifier: Programming Language :: Python :: 3.9
Classifier: Programming Language :: Python :: 3.10
Classifier: Programming Language :: Python :: 3.11
Classifier: Programming Language :: Python :: 3.12
Requires-Dist: PyYAML (>=6.0,<7.0)
Requires-Dist: aws-cfn-custom-resource-resolve-parser (>=0.3,<0.4)
Requires-Dist: cfn-resource-provider (>=1.0.7,<2.0.0)
Requires-Dist: compose-x-common (>=1.4,<2.0)
Requires-Dist: confluent-kafka (>=2.3,<3.0)
Requires-Dist: datamodel-code-generator[http] (>=0.25,<0.26)
Requires-Dist: importlib-resources (>=6.0,<7.0)
Requires-Dist: jsonschema (>=4.21,<5.0)
Requires-Dist: kafka-schema-registry-admin (>=0.5,<0.6)
Requires-Dist: pydantic (==1.10.15)
Requires-Dist: retry2 (>=0.9.5,<0.10.0)
Requires-Dist: troposphere (>=4.5.1,<5.0.0)
Project-URL: Bug Tracker, https://github.com/compose-x/cfn-kafka-admin/issues
Project-URL: Source, https://github.com/compose-x/cfn-kafka-admin
